django_nordigen/__init__.py
django_nordigen/admin.py
django_nordigen/api.py
django_nordigen/apps.py
django_nordigen/management/commands/nordigen_institutions.py
django_nordigen/management/commands/nordigen_requisition.py
django_nordigen/management/commands/nordigen_sync.py
django_nordigen/migrations/0001_initial.py
django_nordigen/migrations/0002_institution_requisition.py
django_nordigen/migrations/0003_account.py
django_nordigen/migrations/0004_transaction.py
django_nordigen/migrations/0005_balance.py
django_nordigen/migrations/0006_requisition_max_historical_days.py
django_nordigen/migrations/0007_alter_transaction_nordigen_id_and_more.py
django_nordigen/migrations/0008_balance_type.py
django_nordigen/migrations/0009_alter_transaction_options.py
django_nordigen/migrations/0010_account_synced_at.py
django_nordigen/migrations/0011_alter_account_nordigen_id_and_more.py
django_nordigen/migrations/0012_account_alias.py
django_nordigen/migrations/__init__.py
django_nordigen/models.py
django_nordigen/templates/admin/django_nordigen/change_form.html
django_nordigen/urls.py
django_nordigen/views.py
django_nordigen-0.1.0.dist-info/METADATA
django_nordigen-0.1.0.dist-info/WHEEL
django_nordigen-0.1.0.dist-info/RECORD
