Metadata-Version: 2.1
Name: django-nordigen
Version: 0.1.0
Summary: 
Author: Alex Morega
Author-email: alex@grep.ro
Requires-Python: >=3.10,<4.0
Classifier: Programming Language :: Python :: 3
Classifier: Programming Language :: Python :: 3.10
Classifier: Programming Language :: Python :: 3.11
Requires-Dist: django (>=4.1.7,<5.0.0)
Requires-Dist: nordigen (>=1.3.0,<2.0.0)
